bigmlflow/__init__.py
bigmlflow/bigml.py
bigmlflow/version.py
bigmlflow-1.0.2.dist-info/LICENSE
bigmlflow-1.0.2.dist-info/METADATA
bigmlflow-1.0.2.dist-info/WHEEL
bigmlflow-1.0.2.dist-info/top_level.txt
bigmlflow-1.0.2.dist-info/RECORD
