Metadata-Version: 2.1
Name: bigmlflow
Version: 1.0.2
Summary: An open source library to add BigML models to the MLFlow API
Home-page: https://bigml.com/
Download-URL: https://github.com/bigmlcom/bigmlflow
Author: The BigML Team
Author-email: bigml@bigml.com
License: http://www.apache.org/licenses/LICENSE-2.0
Classifier: Development Status :: 4 - Beta
Classifier: Intended Audience :: Developers
Classifier: License :: OSI Approved :: Apache Software License
Classifier: Natural Language :: English
Classifier: Operating System :: OS Independent
Classifier: Programming Language :: Python
Classifier: Programming Language :: Python :: 3
Classifier: Topic :: Software Development :: Libraries :: Python Modules
Requires-Python: >=3.7
License-File: LICENSE
Requires-Dist: requests (>=2.28.0)
Requires-Dist: mlflow (>=2.0.1)
Requires-Dist: bigml
Provides-Extra: test
Requires-Dist: pytest ; extra == 'test'
